ddeq/__init__.py
ddeq/amf.py
ddeq/background.py
ddeq/coco2.py
ddeq/csf.py
ddeq/curves.py
ddeq/div.py
ddeq/download_S5P.py
ddeq/dplume.py
ddeq/emissions.py
ddeq/era5.py
ddeq/era5_v2.py
ddeq/era5dl.py
ddeq/functions.py
ddeq/gauss.py
ddeq/ime.py
ddeq/lcsf.py
ddeq/mcmc_tools.py
ddeq/misc.py
ddeq/nox.py
ddeq/plume_coords.py
ddeq/sats.py
ddeq/smartcarb.py
ddeq/solver.py
ddeq/sources.py
ddeq/timeseries.py
ddeq/vis.py
ddeq/wind.py
ddeq/data/ERA5-pbl-20150401t1200.nc
ddeq/data/ERA5_L137_model_level_definitions.csv
ddeq/data/INPUT_ORG
ddeq/data/Matimba_ERA5-pl-20210725.nc
ddeq/data/Matimba_ERA5-sl-20210725.nc
ddeq/data/Matimba_ERA5-wind-20150401t1200.nc
ddeq/data/Matimba_S5P_RPRO_L2__NO2____20210725T110715.nc
ddeq/data/SMARTCARB-CO2-emissions.csv
ddeq/data/SMARTCARB-NO2-emissions.csv
ddeq/data/SMARTCARB_CSF_example.nc
ddeq/data/SMARTCARB_DIV_example.nc
ddeq/data/SMARTCARB_ERA5-lvl-20150423t1100.nc
ddeq/data/SMARTCARB_ERA5-sfc-20150423t1100.nc
ddeq/data/SMARTCARB_winds_2015042311.nc
ddeq/data/Sentinel_7_CO2_2015042311_o1670_l0483.nc
ddeq/data/cosmo_2d_2015042311.nc
ddeq/data/sources-smartcarb.csv
ddeq/data/sources.csv
ddeq/data/coco2_ps_database/README
ddeq/data/coco2_ps_database/README.docx
ddeq/data/coco2_ps_database/coco2_ps_catalogue_v1.1.csv
ddeq/data/coco2_ps_database/coco2_ps_hourly_profiles_v1.1.csv
ddeq/data/coco2_ps_database/coco2_ps_monthly_profiles_v1.1.csv
ddeq/data/coco2_ps_database/coco2_ps_vertical_profiles_v1.1.csv
ddeq/data/coco2_ps_database/coco2_ps_weekly_profiles_v1.1.csv
ddeq-1.1.dist-info/licenses/LICENSE
ddeq-1.1.dist-info/METADATA
ddeq-1.1.dist-info/WHEEL
ddeq-1.1.dist-info/top_level.txt
ddeq-1.1.dist-info/RECORD
