Metadata-Version: 2.4
Name: ddeq
Version: 1.1
Summary: Algorithms for data-driven detection and quantification of hot spot emissions in satellite observations.
Author: Laia Amorós, Grégoire Broquet, Dominik Brunner, Frédéric Chevallier, Janne Hakkarainen, Erik Koene, Gerrit Kuhlmann, Sandro Meier, Janne Nurmela, Diego Santaren, Johanna Tamminen
Maintainer-email: Gerrit Kuhlmann <gerrit.kuhlmann@empa.ch>
Project-URL: Homepage, https://gitlab.com/empa503/remote-sensing/ddeq
Project-URL: Bug Tracker, https://gitlab.com/empa503/remote-sensing/ddeq/-/issues
Classifier: Programming Language :: Python :: 3
Classifier: License :: OSI Approved :: GNU Lesser General Public License v2 or later (LGPLv2+)
Classifier: Operating System :: OS Independent
Requires-Python: >=3.9
License-File: LICENSE
Requires-Dist: cartopy
Requires-Dist: cdsapi
Requires-Dist: diplib
Requires-Dist: f90nml
Requires-Dist: geopandas
Requires-Dist: lmfit
Requires-Dist: matplotlib
Requires-Dist: netCDF4
Requires-Dist: numpy
Requires-Dist: onnxruntime
Requires-Dist: ipywidgets
Requires-Dist: pandas
Requires-Dist: requests
Requires-Dist: scipy
Requires-Dist: shapely>=1.8.0
Requires-Dist: scikit-image>=0.16.2
Requires-Dist: tqdm
Requires-Dist: ucat>=0.2
Requires-Dist: xarray
Provides-Extra: doc
Requires-Dist: enum-tools; extra == "doc"
Requires-Dist: sphinx; extra == "doc"
Requires-Dist: nbsphinx; extra == "doc"
Requires-Dist: furo; extra == "doc"
Requires-Dist: sphinx_toolbox; extra == "doc"
Requires-Dist: ipykernel; extra == "doc"
Requires-Dist: IPython; extra == "doc"
Provides-Extra: dev
Requires-Dist: black; extra == "dev"
Dynamic: license-file
